example_python_package_Blitan/__init__.py
example_python_package_Blitan/core.py
example_python_package_Blitan-0.0.5.dist-info/LICENSE
example_python_package_Blitan-0.0.5.dist-info/METADATA
example_python_package_Blitan-0.0.5.dist-info/WHEEL
example_python_package_Blitan-0.0.5.dist-info/top_level.txt
example_python_package_Blitan-0.0.5.dist-info/RECORD
