Metadata-Version: 2.1
Name: example-python-package-Blitan
Version: 0.0.5
Summary: XXX Skeleton python project example.
Home-page: https://github.com/Blitan/example_python_package_Blitan
Author: Keir
Author-email: keirhearn@gmail.com
License: MIT
Platform: UNKNOWN
